hostify/__init__.py
hostify/cli.py
hostify/cloudflare.py
hostify/cloudflared.py
hostify/host.py
hostify/utils.py
hostify-0.2.1.dist-info/licenses/LICENSE
hostify-0.2.1.dist-info/METADATA
hostify-0.2.1.dist-info/WHEEL
hostify-0.2.1.dist-info/entry_points.txt
hostify-0.2.1.dist-info/top_level.txt
hostify-0.2.1.dist-info/RECORD
