Metadata-Version: 2.4
Name: hostify
Version: 0.2.1
Summary: Effortless application hosting using Cloudflare Tunnels.
Home-page: https://github.com/yuvrajarora1805/hostify
Author: Yuvraj Arora
Author-email: Yuvraj Arora <yuvrajaroraw18@gmail.com>
License: MIT
Project-URL: Homepage, https://github.com/yuvrajarora1805/hostify
Project-URL: Documentation, https://github.com/yuvrajarora1805/hostify#readme
Project-URL: Repository, https://github.com/yuvrajarora1805/hostify
Project-URL: Issues, https://github.com/yuvrajarora1805/hostify/issues
Keywords: cloudflare,tunnel,hosting,server,deployment
Classifier: Development Status :: 3 - Alpha
Classifier: Intended Audience :: Developers
Classifier: Topic :: Internet :: WWW/HTTP :: HTTP Servers
Classifier: License :: OSI Approved :: MIT License
Classifier: Programming Language :: Python :: 3
Classifier: Programming Language :: Python :: 3.9
Classifier: Programming Language :: Python :: 3.10
Classifier: Programming Language :: Python :: 3.11
Classifier: Programming Language :: Python :: 3.12
Classifier: Programming Language :: Python :: 3.13
Requires-Python: >=3.9
License-File: LICENSE
Requires-Dist: requests>=2.28.0
Dynamic: author
Dynamic: home-page
Dynamic: license-file
Dynamic: requires-python
